pygamecv/__init__.py
pygamecv/common.py
pygamecv/draw.py
pygamecv/effect.py
pygame_cv-1.3.2.dist-info/LICENSE
pygame_cv-1.3.2.dist-info/METADATA
pygame_cv-1.3.2.dist-info/WHEEL
pygame_cv-1.3.2.dist-info/top_level.txt
pygame_cv-1.3.2.dist-info/RECORD
